{
  "reddit": {
    "subreddits": [
      { "name": "wallstreetbets", "tier": 1, "weight": 1.5 },
      { "name": "stocks", "tier": 1, "weight": 1.3 },
      { "name": "technology", "tier": 1, "weight": 1.2 },
      { "name": "ClaudeAI", "tier": 2, "weight": 1.0 },
      { "name": "programming", "tier": 2, "weight": 0.8 },
      { "name": "investing", "tier": 2, "weight": 1.0 },
      { "name": "options", "tier": 2, "weight": 1.1 },
      { "name": "SecurityAnalysis", "tier": 3, "weight": 0.7 },
      { "name": "algotrading", "tier": 3, "weight": 0.8 }
    ],
    "postsPerSub": 25,
    "userAgent": "WireSocialScanner/1.0"
  },
  "hn": {
    "enabled": true,
    "topStoriesCount": 30
  },
  "signals": {
    "productLaunch": {
      "keywords": ["just dropped", "launching", "announced", "released", "unveils", "introduces", "rolls out", "now available", "ships today"],
      "weight": 2.0,
      "type": "event"
    },
    "partnership": {
      "keywords": ["partners with", "partnership", "collaboration", "joint venture", "teams up", "deal with", "acquires", "acquisition", "merger"],
      "weight": 1.8,
      "type": "event"
    },
    "regulatory": {
      "keywords": ["SEC", "FDA approval", "antitrust", "regulation", "banned", "lawsuit", "investigation", "subpoena", "compliance"],
      "weight": 2.5,
      "type": "risk"
    },
    "competitiveThreat": {
      "keywords": ["competitor", "disrupts", "obsolete", "replaced by", "better than", "kills", "threatens", "alternative to"],
      "weight": 2.2,
      "type": "threat"
    },
    "sentiment": {
      "keywords": ["to the moon", "bearish", "bullish", "short squeeze", "crash", "pump", "dump", "diamond hands", "paper hands"],
      "weight": 0.8,
      "type": "sentiment"
    }
  },
  "minScore": 1.5,
  "requestDelayMs": 1200
}
